iracing_garage/__init__.py
iracing_garage/client.py
iracing_garage/endpoints.py
iracing_garage/helpers.py
iracing_garage/transport.py
iracing_garage/api_clients/__init__.py
iracing_garage/api_clients/car_client.py
iracing_garage/api_clients/carclass_client.py
iracing_garage/api_clients/constants_client.py
iracing_garage/api_clients/hosted_client.py
iracing_garage/api_clients/league_client.py
iracing_garage/api_clients/lookup_client.py
iracing_garage/api_clients/member_client.py
iracing_garage/api_clients/results_client.py
iracing_garage/api_clients/season_client.py
iracing_garage/api_clients/series_client.py
iracing_garage/api_clients/stats_client.py
iracing_garage/api_clients/team_client.py
iracing_garage/api_clients/time_attack_client.py
iracing_garage/api_clients/track_client.py
iracing_garage-0.0.6.dist-info/LICENSE
iracing_garage-0.0.6.dist-info/METADATA
iracing_garage-0.0.6.dist-info/WHEEL
iracing_garage-0.0.6.dist-info/top_level.txt
iracing_garage-0.0.6.dist-info/RECORD
