Metadata-Version: 2.1
Name: iracing-garage
Version: 0.0.6
Summary: Simple iRacing API Wrapper
Home-page: https://github.com/dangkv/iracing_garage
Author: Dang Khoi Vo
Author-email: <vo.dangkh@gmail.com>
Keywords: python,api,racing,iracing,api-wrappers,iracing-api
Classifier: Programming Language :: Python :: 3
Classifier: Operating System :: Unix
Classifier: Operating System :: MacOS :: MacOS X
Classifier: Operating System :: Microsoft :: Windows
License-File: LICENSE
Requires-Dist: requests
Requires-Dist: requests-toolbelt
